[
  {
    "id": "01JFQ18MP503Q1M1V6B1WGWC15",
    "name": "Mr Ganesh",
    "designation": "Librarian",
    "displayImage": [
      "https://de5byrc8ksekt.cloudfront.net/images/blank-profile-picture-973460_1280.webp"
    ],
    "subtitle": " ",
    "description": " ",
    "mobile": "1234567890",
    "mail": "ganesh@gmail.com",
    "profile": [
      "https://de5byrc8ksekt.cloudfront.net/files/blank-profile-picture-973460_1280.webp"
    ],
    "type": "NON ACADEMIC",
    "metadata": {
      "updated_by": "demo",
      "created_at": "2024-12-22T11:15:29.606Z",
      "updated_at": "2024-12-22T11:15:29.606Z",
      "created_by": "demo"
    },
    "orderId": "1"
  }
]