[
  {
    "id": "01JGM5H4SWXNTN00ZEMGK6SHJE",
    "name": "Ms.S.Hemavathy",
    "course": "M.Phil",
    "areaOfStudy": "Caturvarga Sangraha of Ksemendra - A Study",
    "supervisor": "Dr. T.V. Vasudeva",
    "status": "Completed",
    "metadata": {
      "updated_by": "admin",
      "created_at": "2025-01-02T18:48:01.084Z",
      "updated_at": "2025-01-02T18:48:01.084Z",
      "created_by": "admin"
    },
    "itemPublishStatus": "PUBLISHED"
  },
  {
    "id": "01JGM5H4SWXDXQWHHYM8A4W3F8",
    "name": "Ms. Ramya Bhatt",
    "course": "M.Phil",
    "areaOfStudy": "Significance of Vadavagni",
    "supervisor": "Dr. V. Yamuna Devi",
    "status": "Completed",
    "metadata": {
      "updated_by": "admin",
      "created_at": "2025-01-02T18:48:01.084Z",
      "updated_at": "2025-01-02T18:48:01.084Z",
      "created_by": "admin"
    },
    "itemPublishStatus": "PUBLISHED"
  },
  {
    "id": "01JGM5H4SWS39B7KSS5C3CKXTX",
    "name": "Ms.Brinda Gandhi",
    "course": "M.Phil",
    "areaOfStudy": "Nilakantha Diksita's Vairagyasatakam - A study",
    "supervisor": "Dr. T.V. Vasudeva",
    "status": "Completed",
    "metadata": {
      "updated_by": "admin",
      "created_at": "2025-01-02T18:48:01.084Z",
      "updated_at": "2025-01-02T18:48:01.084Z",
      "created_by": "admin"
    },
    "itemPublishStatus": "PUBLISHED"
  },
  {
    "id": "01JGM5H4SWQKKF66R9D32D0RMD",
    "name": "Ms. Rajalakshmi",
    "course": "M.Phil",
    "areaOfStudy": "Cola Campu",
    "supervisor": "Dr. V. Yamuna Devi",
    "status": "Completed",
    "metadata": {
      "updated_by": "admin",
      "created_at": "2025-01-02T18:48:01.084Z",
      "updated_at": "2025-01-02T18:48:01.084Z",
      "created_by": "admin"
    },
    "itemPublishStatus": "PUBLISHED"
  },
  {
    "id": "01JGM5H4SWNZN2ND69YCN1YQS3",
    "name": "Ms.Vidyuta K",
    "course": "M.Phil",
    "areaOfStudy": "Devaprasada in Vishvakarma Vastushastra",
    "supervisor": "Dr. T.V. Vasudeva",
    "status": "Completed",
    "metadata": {
      "updated_by": "admin",
      "created_at": "2025-01-02T18:48:01.084Z",
      "updated_at": "2025-01-02T18:48:01.084Z",
      "created_by": "admin"
    },
    "itemPublishStatus": "PUBLISHED"
  },
  {
    "id": "01JGM5H4SWCFS23JV5NTSKCJXF",
    "name": "Ms. J Mythili",
    "course": "M.Phil",
    "areaOfStudy": "Yogakundalini Upanisad",
    "supervisor": "Dr. V. Yamuna Devi",
    "status": "Completed",
    "metadata": {
      "updated_by": "admin",
      "created_at": "2025-01-02T18:48:01.084Z",
      "updated_at": "2025-01-02T18:48:01.084Z",
      "created_by": "admin"
    },
    "itemPublishStatus": "PUBLISHED"
  },
  {
    "id": "01JGM5H4SW88MJVC4CVQG93CBV",
    "name": "Ms. Iswarya",
    "course": "M.Phil",
    "areaOfStudy": "Yogacudamani Upanisad- A Critical study",
    "supervisor": "Dr. V. Yamuna Devi",
    "status": "Completed",
    "metadata": {
      "updated_by": "admin",
      "created_at": "2025-01-02T18:48:01.084Z",
      "updated_at": "2025-01-02T18:48:01.084Z",
      "created_by": "admin"
    },
    "itemPublishStatus": "PUBLISHED"
  },
  {
    "id": "01JGM5H4SW6AY3NKM027JR7KVV",
    "name": "Ms. Gowri T",
    "course": "M.Phil",
    "areaOfStudy": "Lingavrtti vicara of Vararuci- A Study",
    "supervisor": "Dr. T.V. Vasudeva",
    "status": "Completed",
    "metadata": {
      "updated_by": "admin",
      "created_at": "2025-01-02T18:48:01.084Z",
      "updated_at": "2025-01-02T18:48:01.084Z",
      "created_by": "admin"
    },
    "itemPublishStatus": "PUBLISHED"
  },
  {
    "id": "01JGM5H4SW5T2TS1EBNXSEBE6T",
    "name": "Ms. Latha",
    "course": "M.Phil",
    "areaOfStudy": "Krishnabhupaliyam",
    "supervisor": "Dr. V. Yamuna Devi",
    "status": "Completed",
    "metadata": {
      "updated_by": "admin",
      "created_at": "2025-01-02T18:48:01.084Z",
      "updated_at": "2025-01-02T18:48:01.084Z",
      "created_by": "admin"
    },
    "itemPublishStatus": "PUBLISHED"
  },
  {
    "id": "01JGM5H4SW4J2CN1VQV6P16ARV",
    "name": "Ms. M. Archana",
    "course": "M.Phil",
    "areaOfStudy": "Unmattaraghava of Virupaksa - A Study",
    "supervisor": "Dr. T.V. Vasudeva",
    "status": "Completed",
    "metadata": {
      "updated_by": "admin",
      "created_at": "2025-01-02T18:48:01.084Z",
      "updated_at": "2025-01-02T18:48:01.084Z",
      "created_by": "admin"
    },
    "itemPublishStatus": "PUBLISHED"
  },
  {
    "id": "01JGM5H4SW48YQ8FWT1GWKK74D",
    "name": "Mr.G.Venkataraman",
    "course": "M.Phil",
    "areaOfStudy": "Sevya Sevakopadesa of Ksemendra - A study",
    "supervisor": "Dr. T.V. Vasudeva",
    "status": "Completed",
    "metadata": {
      "updated_by": "admin",
      "created_at": "2025-01-02T18:48:01.084Z",
      "updated_at": "2025-01-02T18:48:01.084Z",
      "created_by": "admin"
    },
    "itemPublishStatus": "PUBLISHED"
  },
  {
    "id": "01JGM5H4SW0K5YG1QWP697GN6C",
    "name": "Ms. Mrinalini",
    "course": "M.Phil",
    "areaOfStudy": "Sandilyopanisad- A Critical study",
    "supervisor": "Dr. V. Yamuna Devi",
    "status": "Completed",
    "metadata": {
      "updated_by": "admin",
      "created_at": "2025-01-02T18:48:01.084Z",
      "updated_at": "2025-01-02T18:48:01.084Z",
      "created_by": "admin"
    },
    "itemPublishStatus": "PUBLISHED"
  },
  {
    "id": "01JGM5H4SVZK70F41SNG68Q1FD",
    "name": "Mr K.P. Srikanth",
    "course": "M.Phil",
    "areaOfStudy": "Dosapariharas in Brhatparasara Horasastra",
    "supervisor": "Dr. K.S. Balasubramanian",
    "status": "Completed",
    "metadata": {
      "updated_by": "admin",
      "created_at": "2025-01-02T18:48:01.083Z",
      "updated_at": "2025-01-02T18:48:01.083Z",
      "created_by": "admin"
    },
    "itemPublishStatus": "PUBLISHED"
  },
  {
    "id": "01JGM5H4SVTDNZR7AK83MS91ZC",
    "name": "Premavathi",
    "course": "M.Phil",
    "areaOfStudy": "A critical study of Nakshatramala of Sivarama Tripathin with Eng. Trans.",
    "supervisor": "Dr. S.S. Janaki",
    "status": "Completed",
    "metadata": {
      "updated_by": "admin",
      "created_at": "2025-01-02T18:48:01.083Z",
      "updated_at": "2025-01-02T18:48:01.083Z",
      "created_by": "admin"
    },
    "itemPublishStatus": "PUBLISHED"
  },
  {
    "id": "01JGM5H4SVSQ69C09KY65Y7CRQ",
    "name": "N.Ambika",
    "course": "M.Phil",
    "areaOfStudy": "Movement (Gatis) in Natya according to Bharata's Natyasastra.",
    "supervisor": "Dr. S.S. Janaki",
    "status": "Completed",
    "metadata": {
      "updated_by": "admin",
      "created_at": "2025-01-02T18:48:01.083Z",
      "updated_at": "2025-01-02T18:48:01.083Z",
      "created_by": "admin"
    },
    "itemPublishStatus": "PUBLISHED"
  },
  {
    "id": "01JGM5H4SVS96CCTA5TGDCP6R0",
    "name": "Lokanayaki Ammal",
    "course": "M.Phil",
    "areaOfStudy": "Siva elements in Ramayana",
    "supervisor": "Dr. S.S. Janaki",
    "status": "Completed",
    "metadata": {
      "updated_by": "admin",
      "created_at": "2025-01-02T18:48:01.083Z",
      "updated_at": "2025-01-02T18:48:01.083Z",
      "created_by": "admin"
    },
    "itemPublishStatus": "PUBLISHED"
  },
  {
    "id": "01JGM5H4SVRNK57PZACPM6RN6E",
    "name": "V.Vasudevan",
    "course": "M.Phil",
    "areaOfStudy": "Bhramara Kahali-Eng.trans. & study",
    "supervisor": "Dr. S.S. Janaki",
    "status": "Completed",
    "metadata": {
      "updated_by": "admin",
      "created_at": "2025-01-02T18:48:01.083Z",
      "updated_at": "2025-01-02T18:48:01.083Z",
      "created_by": "admin"
    },
    "itemPublishStatus": "PUBLISHED"
  },
  {
    "id": "01JGM5H4SVRBCVPYFPZBJTEVXN",
    "name": "Ms. N. Meena",
    "course": "M.Phil",
    "areaOfStudy": "Code Language in War And Politics",
    "supervisor": "Dr. V. Kameswari",
    "status": "Completed",
    "metadata": {
      "updated_by": "admin",
      "created_at": "2025-01-02T18:48:01.083Z",
      "updated_at": "2025-01-02T18:48:01.083Z",
      "created_by": "admin"
    },
    "itemPublishStatus": "PUBLISHED"
  },
  {
    "id": "01JGM5H4SVMB7Q9DZX8671ZQBV",
    "name": "Ms. S. Anuradha",
    "course": "M.Phil",
    "areaOfStudy": "Varahopanisad",
    "supervisor": "Dr. K.S. Balasubramanian",
    "status": "Completed",
    "metadata": {
      "updated_by": "admin",
      "created_at": "2025-01-02T18:48:01.083Z",
      "updated_at": "2025-01-02T18:48:01.083Z",
      "created_by": "admin"
    },
    "itemPublishStatus": "PUBLISHED"
  },
  {
    "id": "01JGM5H4SVKQXSXM0VNSZ5VKAD",
    "name": "K.Srinivasan",
    "course": "M.Phil",
    "areaOfStudy": "Tripuradaha Dima",
    "supervisor": "Dr. S.S. Janaki",
    "status": "Completed",
    "metadata": {
      "updated_by": "admin",
      "created_at": "2025-01-02T18:48:01.083Z",
      "updated_at": "2025-01-02T18:48:01.083Z",
      "created_by": "admin"
    },
    "itemPublishStatus": "PUBLISHED"
  },
  {
    "id": "01JGM5H4SVH4SYR15FE3XD9W1V",
    "name": "P.K.Bhaskaran",
    "course": "M.Phil",
    "areaOfStudy": "Upakramaparakrama of Appaya Diksita - A critical Study",
    "supervisor": "Dr. S.S. Janaki",
    "status": "Completed",
    "metadata": {
      "updated_by": "admin",
      "created_at": "2025-01-02T18:48:01.083Z",
      "updated_at": "2025-01-02T18:48:01.083Z",
      "created_by": "admin"
    },
    "itemPublishStatus": "PUBLISHED"
  },
  {
    "id": "01JGM5H4SVGGZCBQXVK2WN87TQ",
    "name": "G.Meenakshi",
    "course": "M.Phil",
    "areaOfStudy": "A critical study of Vakrokti Pancasika of Ratnakara",
    "supervisor": "Dr. S.S. Janaki",
    "status": "Completed",
    "metadata": {
      "updated_by": "admin",
      "created_at": "2025-01-02T18:48:01.083Z",
      "updated_at": "2025-01-02T18:48:01.083Z",
      "created_by": "admin"
    },
    "itemPublishStatus": "PUBLISHED"
  },
  {
    "id": "01JGM5H4SVF0VDWY9H15XBAGMS",
    "name": "B.Ramadevi",
    "course": "M.Phil",
    "areaOfStudy": "Ganjifa Khelana of Giridhara - A study",
    "supervisor": "Dr. V. Kameswari",
    "status": "Completed",
    "metadata": {
      "updated_by": "admin",
      "created_at": "2025-01-02T18:48:01.083Z",
      "updated_at": "2025-01-02T18:48:01.083Z",
      "created_by": "admin"
    },
    "itemPublishStatus": "PUBLISHED"
  },
  {
    "id": "01JGM5H4SVEB7XBEM45XQ8KY62",
    "name": "Ms.S.Padmapriya",
    "course": "M.Phil",
    "areaOfStudy": "Karani in Ganitasastra - An analysis",
    "supervisor": "Dr. K.S. Balasubramanian",
    "status": "Completed",
    "metadata": {
      "updated_by": "admin",
      "created_at": "2025-01-02T18:48:01.083Z",
      "updated_at": "2025-01-02T18:48:01.083Z",
      "created_by": "admin"
    },
    "itemPublishStatus": "PUBLISHED"
  },
  {
    "id": "01JGM5H4SVD6RR92H34J954S1H",
    "name": "Ms.Vibha Raghav",
    "course": "M.Phil",
    "areaOfStudy": "Goraksha Samhita - A Critical Study",
    "supervisor": "Dr. K.S. Balasubramanian",
    "status": "Completed",
    "metadata": {
      "updated_by": "admin",
      "created_at": "2025-01-02T18:48:01.083Z",
      "updated_at": "2025-01-02T18:48:01.083Z",
      "created_by": "admin"
    },
    "itemPublishStatus": "PUBLISHED"
  },
  {
    "id": "01JGM5H4SVCARSPBYF3WHFZWFC",
    "name": "Ms. S. Anusha",
    "course": "M.Phil",
    "areaOfStudy": "Critical Analysis of Drstanta-kalikasataka",
    "supervisor": "Dr. T.V. Vasudeva",
    "status": "Completed",
    "metadata": {
      "updated_by": "admin",
      "created_at": "2025-01-02T18:48:01.084Z",
      "updated_at": "2025-01-02T18:48:01.084Z",
      "created_by": "admin"
    },
    "itemPublishStatus": "PUBLISHED"
  },
  {
    "id": "01JGM5H4SVAW47D1PDCD5TKFHE",
    "name": "R.Subasri",
    "course": "M.Phil",
    "areaOfStudy": "Irony in Sanskrit Literature",
    "supervisor": "Dr. V. Kameswari",
    "status": "Completed",
    "metadata": {
      "updated_by": "admin",
      "created_at": "2025-01-02T18:48:01.083Z",
      "updated_at": "2025-01-02T18:48:01.083Z",
      "created_by": "admin"
    },
    "itemPublishStatus": "PUBLISHED"
  },
  {
    "id": "01JGM5H4SV80SXW89R7E2TMKQ6",
    "name": "Mr. S. Nagarajan",
    "course": "M.Phil",
    "areaOfStudy": "Yogapada of Matanga Parameswaragama",
    "supervisor": "Dr. K.S. Balasubramanian",
    "status": "Completed",
    "metadata": {
      "updated_by": "admin",
      "created_at": "2025-01-02T18:48:01.083Z",
      "updated_at": "2025-01-02T18:48:01.083Z",
      "created_by": "admin"
    },
    "itemPublishStatus": "PUBLISHED"
  },
  {
    "id": "01JGM5H4SV5AG7P1NQCPNYR464",
    "name": "N.Sridhar",
    "course": "M.Phil",
    "areaOfStudy": "Lilavati Vithi- A Critical study",
    "supervisor": "Dr. S.S. Janaki",
    "status": "Completed",
    "metadata": {
      "updated_by": "admin",
      "created_at": "2025-01-02T18:48:01.083Z",
      "updated_at": "2025-01-02T18:48:01.083Z",
      "created_by": "admin"
    },
    "itemPublishStatus": "PUBLISHED"
  },
  {
    "id": "01JGM5H4SV2YGJBR00MRDHM90J",
    "name": "Ms. V. Premalatha",
    "course": "M.Phil",
    "areaOfStudy": "Amanaska Yoga - A Critical Study",
    "supervisor": "Dr. V. Kameswari",
    "status": "Completed",
    "metadata": {
      "updated_by": "admin",
      "created_at": "2025-01-02T18:48:01.083Z",
      "updated_at": "2025-01-02T18:48:01.083Z",
      "created_by": "admin"
    },
    "itemPublishStatus": "PUBLISHED"
  },
  {
    "id": "01JGM5H4SV2P4W00E930S83K3Z",
    "name": "G.D.Jayalakshmi",
    "course": "M.Phil",
    "areaOfStudy": "Rukminiharana of Vatsaraja",
    "supervisor": "Dr. S.S. Janaki",
    "status": "Completed",
    "metadata": {
      "updated_by": "admin",
      "created_at": "2025-01-02T18:48:01.083Z",
      "updated_at": "2025-01-02T18:48:01.083Z",
      "created_by": "admin"
    },
    "itemPublishStatus": "PUBLISHED"
  },
  {
    "id": "01JGM5H4SV27YHR4J0HMR7SBDN",
    "name": "Hema Ramanathan",
    "course": "M.Phil",
    "areaOfStudy": "Comparative study of the poetics of Anandavardhana and Susanne Langer",
    "supervisor": "Dr. S.S. Janaki",
    "status": "Completed",
    "metadata": {
      "updated_by": "admin",
      "created_at": "2025-01-02T18:48:01.083Z",
      "updated_at": "2025-01-02T18:48:01.083Z",
      "created_by": "admin"
    },
    "itemPublishStatus": "PUBLISHED"
  },
  {
    "id": "01JGM5H4SV21BZT82YZMTV6ZN7",
    "name": "Mr. K. Nagarajan",
    "course": "M.Phil",
    "areaOfStudy": "Yogabija",
    "supervisor": "Dr. K.S. Balasubramanian",
    "status": "Completed",
    "metadata": {
      "updated_by": "admin",
      "created_at": "2025-01-02T18:48:01.083Z",
      "updated_at": "2025-01-02T18:48:01.083Z",
      "created_by": "admin"
    },
    "itemPublishStatus": "PUBLISHED"
  },
  {
    "id": "01JGM5H4SV1TW3V3N9QWGFYWE0",
    "name": "Ms. A. Yamuna Devi",
    "course": "M.Phil",
    "areaOfStudy": "Critical Edition and Study of Paniniya Sutrodaharana Kavya",
    "supervisor": "Dr. V. Kameswari",
    "status": "Completed",
    "metadata": {
      "updated_by": "admin",
      "created_at": "2025-01-02T18:48:01.083Z",
      "updated_at": "2025-01-02T18:48:01.083Z",
      "created_by": "admin"
    },
    "itemPublishStatus": "PUBLISHED"
  },
  {
    "id": "01JGM5H4SV1QM6369H9EABAST5",
    "name": "Mr.S.Margabandhu",
    "course": "M.Phil",
    "areaOfStudy": "Yogic elements in Mrgendra Agama",
    "supervisor": "Dr. K.S. Balasubramanian",
    "status": "Completed",
    "metadata": {
      "updated_by": "admin",
      "created_at": "2025-01-02T18:48:01.083Z",
      "updated_at": "2025-01-02T18:48:01.083Z",
      "created_by": "admin"
    },
    "itemPublishStatus": "PUBLISHED"
  },
  {
    "id": "01JGM5H4SV0B0GBBF2C0DXJKYJ",
    "name": "R.Padmini",
    "course": "M.Phil",
    "areaOfStudy": "Critical study of Candrakala Natika of Viswanatha",
    "supervisor": "Dr. S.S. Janaki",
    "status": "Completed",
    "metadata": {
      "updated_by": "admin",
      "created_at": "2025-01-02T18:48:01.083Z",
      "updated_at": "2025-01-02T18:48:01.083Z",
      "created_by": "admin"
    },
    "itemPublishStatus": "PUBLISHED"
  }
]